benchmarkit/__init__.py
benchmarkit/core.py
benchmarkit/helpers.py
benchmarkit/entrypoints/__init__.py
benchmarkit/entrypoints/analyze.py
benchmarkit/entrypoints/run.py
benchmarkit-0.0.4.dist-info/LICENSE
benchmarkit-0.0.4.dist-info/METADATA
benchmarkit-0.0.4.dist-info/WHEEL
benchmarkit-0.0.4.dist-info/entry_points.txt
benchmarkit-0.0.4.dist-info/top_level.txt
benchmarkit-0.0.4.dist-info/RECORD
