Metadata-Version: 2.1
Name: benchmarkit
Version: 0.0.4
Summary: Benchmark and analyze functions' time execution and results over the course of development
Home-page: https://github.com/vgrabovets/benchmarkit
Author: Vitaliy Grabovets
Author-email: v.grabovets@gmail.com
License: MIT
Keywords: benchmark,timeit,time
Platform: UNKNOWN
Requires-Python: >=3.6.0
Requires-Dist: colorama (==0.4.1)
Requires-Dist: GitPython (==2.1.15)
Requires-Dist: pandas (==0.24.2)
Requires-Dist: path.py (==12.0.1)
